LICENSE
MANIFEST.in
README.md
setup.py
pyzm/ZMEventNotification.py
pyzm/ZMLog.py
pyzm/ZMMemory.py
pyzm/__init__.py
pyzm/api.py
pyzm.egg-info/PKG-INFO
pyzm.egg-info/SOURCES.txt
pyzm.egg-info/dependency_links.txt
pyzm.egg-info/requires.txt
pyzm.egg-info/top_level.txt
pyzm/helpers/Base.py
pyzm/helpers/Configs.py
pyzm/helpers/Event.py
pyzm/helpers/Events.py
pyzm/helpers/Media.py
pyzm/helpers/Monitor.py
pyzm/helpers/Monitors.py
pyzm/helpers/State.py
pyzm/helpers/States.py
pyzm/helpers/globals.py
pyzm/helpers/utils.py
pyzm/ml/alpr.py
pyzm/ml/aws_rekognition.py
pyzm/ml/coral_edgetpu.py
pyzm/ml/detect_sequence.py
pyzm/ml/face.py
pyzm/ml/face_dlib.py
pyzm/ml/face_tpu.py
pyzm/ml/face_train_dlib.py
pyzm/ml/hog.py
pyzm/ml/object.py
pyzm/ml/virelai.py
pyzm/ml/yolo.py